fabric_forked/__init__.py
fabric_forked/__main__.py
fabric_forked/_types.pyi
fabric_forked/_version.py
fabric_forked/auth.py
fabric_forked/auth.pyi
fabric_forked/config.py
fabric_forked/config.pyi
fabric_forked/connection.py
fabric_forked/connection.pyi
fabric_forked/exceptions.py
fabric_forked/executor.py
fabric_forked/executor.pyi
fabric_forked/group.py
fabric_forked/group.pyi
fabric_forked/main.py
fabric_forked/runners.py
fabric_forked/runners.pyi
fabric_forked/tasks.py
fabric_forked/tasks.pyi
fabric_forked/transfer.py
fabric_forked/transfer.pyi
fabric_forked/tunnels.py
fabric_forked/tunnels.pyi
fabric_forked/util.py
fabric_forked-3.2.2.post2.dist-info/LICENSE
fabric_forked-3.2.2.post2.dist-info/METADATA
fabric_forked-3.2.2.post2.dist-info/WHEEL
fabric_forked-3.2.2.post2.dist-info/RECORD
