Metadata-Version: 2.1
Name: fabric-forked
Version: 3.2.2.post2
Summary: High level SSH command execution (forked by 'fabric').
License: MIT
Author: Romanin
Author-email: semina054@gmail.com
Maintainer: Jeff Forcier
Maintainer-email: jeff@bitprophet.org
Requires-Python: >=3.10
Classifier: Development Status :: 5 - Production/Stable
Classifier: Environment :: Console
Classifier: Intended Audience :: Developers
Classifier: Intended Audience :: System Administrators
Classifier: License :: OSI Approved :: BSD License
Classifier: License :: OSI Approved :: MIT License
Classifier: Operating System :: MacOS :: MacOS X
Classifier: Operating System :: Microsoft :: Windows
Classifier: Operating System :: POSIX
Classifier: Operating System :: Unix
Classifier: Programming Language :: Python :: 3
Classifier: Programming Language :: Python :: 3.10
Classifier: Programming Language :: Python :: 3.11
Classifier: Programming Language :: Python :: 3.12
Classifier: Programming Language :: Python :: 3.13
Classifier: Topic :: Software Development
Classifier: Topic :: Software Development :: Build Tools
Classifier: Topic :: Software Development :: Libraries
Classifier: Topic :: Software Development :: Libraries :: Python Modules
Classifier: Topic :: System :: Clustering
Classifier: Topic :: System :: Software Distribution
Classifier: Topic :: System :: Systems Administration
Provides-Extra: pytest
Requires-Dist: decorator (>=5.1.1,<6.0.0)
Requires-Dist: invoke (>=2.2.0,<3.0.0)
Requires-Dist: paramiko (>=3.5.0,<4.0.0)
Requires-Dist: typing-extensions (>=4.12.2,<5.0.0)
